{"_invocation_id": "35e7f40e-ef28-426a-96a7-96ffa8d671ca", "linked": {"0": {"name": "source.patreon_analytics.raw_patreon.creators", "type": "source", "succ": [10, 59, 60]}, "1": {"name": "source.patreon_analytics.raw_patreon.patrons", "type": "source", "succ": [13, 61, 62]}, "2": {"name": "source.patreon_analytics.raw_patreon.tiers", "type": "source", "succ": [9, 63, 64]}, "3": {"name": "source.patreon_analytics.raw_patreon.pledges", "type": "source", "succ": [11, 65, 66]}, "4": {"name": "source.patreon_analytics.raw_patreon.transactions", "type": "source", "succ": [7, 67, 68]}, "5": {"name": "source.patreon_analytics.raw_patreon.posts", "type": "source", "succ": [8, 69, 70]}, "6": {"name": "source.patreon_analytics.raw_patreon.engagement_events", "type": "source", "succ": [12, 71, 72]}, "7": {"name": "model.patreon_analytics.stg_transactions", "type": "model", "succ": [14, 42, 43, 44, 45, 46]}, "8": {"name": "model.patreon_analytics.stg_posts", "type": "model", "succ": [14, 47, 48, 49, 50]}, "9": {"name": "model.patreon_analytics.stg_tiers", "type": "model", "succ": [14, 30, 31, 32, 33, 34]}, "10": {"name": "model.patreon_analytics.stg_creators", "type": "model", "succ": [14, 23, 24, 25, 26, 33, 40, 50]}, "11": {"name": "model.patreon_analytics.stg_pledges", "type": "model", "succ": [14, 35, 36, 37, 38, 39, 40, 41]}, "12": {"name": "model.patreon_analytics.stg_engagement_events", "type": "model", "succ": [14, 51, 52, 53]}, "13": {"name": "model.patreon_analytics.stg_patrons", "type": "model", "succ": [27, 28, 29, 38]}, "14": {"name": "model.patreon_analytics.fct_creator_monthly_performance", "type": "model", "succ": [54, 55, 56, 57, 58, 73]}, "15": {"name": "model.patreon_analytics.metricflow_time_spine", "type": "model"}, "16": {"name": "seed.patreon_analytics.posts", "type": "seed"}, "17": {"name": "seed.patreon_analytics.patrons", "type": "seed"}, "18": {"name": "seed.patreon_analytics.tiers", "type": "seed"}, "19": {"name": "seed.patreon_analytics.pledges", "type": "seed"}, "20": {"name": "seed.patreon_analytics.transactions", "type": "seed"}, "21": {"name": "seed.patreon_analytics.engagement_events", "type": "seed"}, "22": {"name": "seed.patreon_analytics.creators", "type": "seed"}, "23": {"name": "test.patreon_analytics.unique_stg_creators_creator_id.78aaa0dba4", "type": "test"}, "24": {"name": "test.patreon_analytics.not_null_stg_creators_creator_id.a4d196188a", "type": "test"}, "25": {"name": "test.patreon_analytics.accepted_values_stg_creators_plan_type__lite__pro__premium.3492742776", "type": "test"}, "26": {"name": "test.patreon_analytics.accepted_values_stg_creators_status__active__paused__suspended__deleted.7a24db0237", "type": "test"}, "27": {"name": "test.patreon_analytics.unique_stg_patrons_patron_id.b6b0671565", "type": "test"}, "28": {"name": "test.patreon_analytics.not_null_stg_patrons_patron_id.9a81327dee", "type": "test"}, "29": {"name": "test.patreon_analytics.accepted_values_stg_patrons_patron_value_tier__whale__high_value__regular__casual.3f5dae4aa6", "type": "test"}, "30": {"name": "test.patreon_analytics.unique_stg_tiers_tier_id.edaf87f122", "type": "test"}, "31": {"name": "test.patreon_analytics.not_null_stg_tiers_tier_id.a8da115175", "type": "test"}, "32": {"name": "test.patreon_analytics.not_null_stg_tiers_creator_id.03c2bb8892", "type": "test"}, "33": {"name": "test.patreon_analytics.relationships_stg_tiers_creator_id__creator_id__ref_stg_creators_.d7715cdf0a", "type": "test"}, "34": {"name": "test.patreon_analytics.not_null_stg_tiers_price_usd.41c4bc4c96", "type": "test"}, "35": {"name": "test.patreon_analytics.unique_stg_pledges_pledge_id.d71e65eb4c", "type": "test"}, "36": {"name": "test.patreon_analytics.not_null_stg_pledges_pledge_id.c6c8840915", "type": "test"}, "37": {"name": "test.patreon_analytics.not_null_stg_pledges_patron_id.45079734da", "type": "test"}, "38": {"name": "test.patreon_analytics.relationships_stg_pledges_patron_id__patron_id__ref_stg_patrons_.1aea46a3f2", "type": "test"}, "39": {"name": "test.patreon_analytics.not_null_stg_pledges_creator_id.7ac5bc19ef", "type": "test"}, "40": {"name": "test.patreon_analytics.relationships_stg_pledges_creator_id__creator_id__ref_stg_creators_.a296b68aa7", "type": "test"}, "41": {"name": "test.patreon_analytics.accepted_values_stg_pledges_pledge_status__active__paused__churned__declined.a38baa5be6", "type": "test"}, "42": {"name": "test.patreon_analytics.unique_stg_transactions_transaction_id.ee9a78a396", "type": "test"}, "43": {"name": "test.patreon_analytics.not_null_stg_transactions_transaction_id.1d00a8e2e4", "type": "test"}, "44": {"name": "test.patreon_analytics.not_null_stg_transactions_pledge_id.176713ed98", "type": "test"}, "45": {"name": "test.patreon_analytics.accepted_values_stg_transactions_transaction_status__pending__succeeded__failed__refunded.93b1b6f227", "type": "test"}, "46": {"name": "test.patreon_analytics.accepted_values_stg_transactions_transaction_type__pledge_payment__refund__chargeback.1ac4aaca05", "type": "test"}, "47": {"name": "test.patreon_analytics.unique_stg_posts_post_id.ec6994c39f", "type": "test"}, "48": {"name": "test.patreon_analytics.not_null_stg_posts_post_id.cd5975e2d9", "type": "test"}, "49": {"name": "test.patreon_analytics.not_null_stg_posts_creator_id.44240e5ecf", "type": "test"}, "50": {"name": "test.patreon_analytics.relationships_stg_posts_creator_id__creator_id__ref_stg_creators_.ef48439d1e", "type": "test"}, "51": {"name": "test.patreon_analytics.unique_stg_engagement_events_event_id.04a2222875", "type": "test"}, "52": {"name": "test.patreon_analytics.not_null_stg_engagement_events_event_id.a363dfdd90", "type": "test"}, "53": {"name": "test.patreon_analytics.accepted_values_stg_engagement_events_event_type__view__like__unlike__comment__share.6f1a4c0604", "type": "test"}, "54": {"name": "test.patreon_analytics.unique_fct_creator_monthly_performance_creator_month_key.e5e4345d05", "type": "test"}, "55": {"name": "test.patreon_analytics.not_null_fct_creator_monthly_performance_creator_month_key.1c715c9d68", "type": "test"}, "56": {"name": "test.patreon_analytics.not_null_fct_creator_monthly_performance_creator_id.4643f34720", "type": "test"}, "57": {"name": "test.patreon_analytics.not_null_fct_creator_monthly_performance_month_start_date.ed79aa56db", "type": "test"}, "58": {"name": "test.patreon_analytics.accepted_values_fct_creator_monthly_performance_plan_type__lite__pro__premium.1487829c6d", "type": "test"}, "59": {"name": "test.patreon_analytics.source_unique_raw_patreon_creators_creator_id.021e36ab38", "type": "test"}, "60": {"name": "test.patreon_analytics.source_not_null_raw_patreon_creators_creator_id.973eda54d5", "type": "test"}, "61": {"name": "test.patreon_analytics.source_unique_raw_patreon_patrons_patron_id.fce6643094", "type": "test"}, "62": {"name": "test.patreon_analytics.source_not_null_raw_patreon_patrons_patron_id.2e93a6c0cc", "type": "test"}, "63": {"name": "test.patreon_analytics.source_unique_raw_patreon_tiers_tier_id.9d03e86958", "type": "test"}, "64": {"name": "test.patreon_analytics.source_not_null_raw_patreon_tiers_tier_id.be9bad69eb", "type": "test"}, "65": {"name": "test.patreon_analytics.source_unique_raw_patreon_pledges_pledge_id.22ed9168b4", "type": "test"}, "66": {"name": "test.patreon_analytics.source_not_null_raw_patreon_pledges_pledge_id.4811b752a7", "type": "test"}, "67": {"name": "test.patreon_analytics.source_unique_raw_patreon_transactions_transaction_id.abd5c64ba6", "type": "test"}, "68": {"name": "test.patreon_analytics.source_not_null_raw_patreon_transactions_transaction_id.9159be8f9d", "type": "test"}, "69": {"name": "test.patreon_analytics.source_unique_raw_patreon_posts_post_id.bee1de4d33", "type": "test"}, "70": {"name": "test.patreon_analytics.source_not_null_raw_patreon_posts_post_id.61a25c7b8f", "type": "test"}, "71": {"name": "test.patreon_analytics.source_unique_raw_patreon_engagement_events_event_id.0f270374d7", "type": "test"}, "72": {"name": "test.patreon_analytics.source_not_null_raw_patreon_engagement_events_event_id.2044a41711", "type": "test"}, "73": {"name": "semantic_model.patreon_analytics.creator_performance", "type": "semantic_model", "succ": [74, 75, 76]}, "74": {"name": "metric.patreon_analytics.platform_total_mrr", "type": "metric"}, "75": {"name": "metric.patreon_analytics.total_platform_fees", "type": "metric", "succ": [77]}, "76": {"name": "metric.patreon_analytics.total_revenue", "type": "metric", "succ": [77]}, "77": {"name": "metric.patreon_analytics.platform_take_rate", "type": "metric"}}}